function_by_svetlanakoroleva/README.md
function_by_svetlanakoroleva/math_functions.py
function_by_svetlanakoroleva-0.4.0.dist-info/WHEEL
function_by_svetlanakoroleva-0.4.0.dist-info/METADATA
function_by_svetlanakoroleva-0.4.0.dist-info/RECORD
