Metadata-Version: 2.1
Name: function-by-svetlanakoroleva
Version: 0.4.0
Summary: This is our test project
Author: Svetlana Koroleva
Author-email: ksvetkaqt@gmail.com
Requires-Python: >=3.10,<4.0
Classifier: Programming Language :: Python :: 3
Classifier: Programming Language :: Python :: 3.10
Classifier: Programming Language :: Python :: 3.11
